mrscfastcom.cp37-win32.pyd
MrscFastComponents-0.0.3.dist-info/METADATA
MrscFastComponents-0.0.3.dist-info/WHEEL
MrscFastComponents-0.0.3.dist-info/top_level.txt
MrscFastComponents-0.0.3.dist-info/RECORD
