Metadata-Version: 2.1
Name: MrscFastComponents
Version: 0.0.3
Summary: Fast Multi-Robot Sorting Centers Components for Prototyping.
Home-page: https://github.com/Username6129/MrscFastComponents
Author: Chee-Henn Chng
Author-email: cheehennchng@gmail.com
License: MIT
Platform: UNKNOWN
Classifier: License :: OSI Approved :: MIT License
